mongo_mcp/__init__.py
mongo_mcp/__main__.py
mongo_mcp/config.py
mongo_mcp/db.py
mongo_mcp/server.py
mongo_mcp/tools/__init__.py
mongo_mcp/tools/database_tools.py
mongo_mcp/tools/document_tools.py
mongo_mcp/utils/__init__.py
mongo_mcp/utils/json_encoder.py
mongo_mcp-0.1.3.dist-info/METADATA
mongo_mcp-0.1.3.dist-info/WHEEL
mongo_mcp-0.1.3.dist-info/entry_points.txt
mongo_mcp-0.1.3.dist-info/licenses/LICENSE
mongo_mcp-0.1.3.dist-info/RECORD
