Metadata-Version: 2.4
Name: mongo-mcp
Version: 0.1.3
Summary: MCP service for MongoDB operations
Project-URL: Homepage, https://github.com/441126098/mongo-mcp
Project-URL: Source, https://github.com/441126098/mongo-mcp
Project-URL: Tracker, https://github.com/441126098/mongo-mcp/issues
Author-email: allenZhang <allenzhang570@gmail.com>
License-File: LICENSE
Requires-Python: >=3.10
Requires-Dist: fastmcp>=0.3.4
Requires-Dist: pymongo>=4.5.0
Provides-Extra: dev
Requires-Dist: black>=23.7.0; extra == 'dev'
Requires-Dist: isort>=5.12.0; extra == 'dev'
Requires-Dist: mypy>=1.5.1; extra == 'dev'
Requires-Dist: pytest>=7.4.0; extra == 'dev'
